ELF_RSS2/__init__.py
ELF_RSS2/command/__init__.py
ELF_RSS2/command/add_cookies.py
ELF_RSS2/command/add_dy.py
ELF_RSS2/command/change_dy.py
ELF_RSS2/command/del_dy.py
ELF_RSS2/command/rsshub_add.py
ELF_RSS2/command/show_all.py
ELF_RSS2/command/show_dy.py
ELF_RSS2/command/upload_group_file.py
ELF_RSS2/config.py
ELF_RSS2/my_trigger.py
ELF_RSS2/parsing/__init__.py
ELF_RSS2/parsing/cache_manage.py
ELF_RSS2/parsing/check_update.py
ELF_RSS2/parsing/download_torrent.py
ELF_RSS2/parsing/handle_html_tag.py
ELF_RSS2/parsing/handle_images.py
ELF_RSS2/parsing/handle_translation.py
ELF_RSS2/parsing/parsing_rss.py
ELF_RSS2/parsing/routes/__init__.py
ELF_RSS2/parsing/routes/bilibili.py
ELF_RSS2/parsing/routes/danbooru.py
ELF_RSS2/parsing/routes/pixiv.py
ELF_RSS2/parsing/routes/south_plus.py
ELF_RSS2/parsing/routes/twitter.py
ELF_RSS2/parsing/routes/weibo.py
ELF_RSS2/parsing/routes/yande_re.py
ELF_RSS2/parsing/routes/youtube.py
ELF_RSS2/parsing/send_message.py
ELF_RSS2/parsing/utils.py
ELF_RSS2/pikpak_offline.py
ELF_RSS2/qbittorrent_download.py
ELF_RSS2/rss_class.py
ELF_RSS2/rss_parsing.py
ELF_RSS2/utils.py
elf_rss-2.6.25.dist-info/LICENSE
elf_rss-2.6.25.dist-info/METADATA
elf_rss-2.6.25.dist-info/WHEEL
elf_rss-2.6.25.dist-info/RECORD
