Metadata-Version: 2.1
Name: ELF_RSS
Version: 2.6.25
Summary: QQ机器人 RSS订阅 插件，订阅源建议选择 RSSHub
Home-page: https://github.com/Quan666/ELF_RSS
License: GPL-3.0-only
Keywords: nonebot,nonebot2,rss,elf,rsshub
Author: Quan666
Author-email: i@Rori.eMail
Requires-Python: >=3.12.6,<4.0.0
Classifier: License :: OSI Approved :: GNU General Public License v3 (GPLv3)
Classifier: Programming Language :: Python :: 3
Requires-Dist: ImageHash (>=4.3.1,<5.0.0)
Requires-Dist: Pillow (>=10.4.0,<11.0.0)
Requires-Dist: aiohttp[speedups] (>=3.10.5,<4.0.0)
Requires-Dist: arrow (>=1.3.0,<2.0.0)
Requires-Dist: async-timeout (>=4.0.3,<5.0.0)
Requires-Dist: bbcode (>=1.1.0,<2.0.0)
Requires-Dist: cachetools (>=5.5.0,<6.0.0)
Requires-Dist: deep-translator (>=1.11.4,<2.0.0)
Requires-Dist: emoji (>=2.12.1,<3.0.0)
Requires-Dist: feedparser (>=6.0.11,<7.0.0)
Requires-Dist: magneturi (>=1.3,<2.0)
Requires-Dist: nonebot-adapter-onebot (>=2.4.4,<3.0.0)
Requires-Dist: nonebot-plugin-apscheduler (>=0.5.0,<0.6.0)
Requires-Dist: nonebot2[fastapi] (>=2.3.3,<3.0.0)
Requires-Dist: pikpakapi (>=0.1.10,<0.2.0)
Requires-Dist: pydantic (>=1.10.18,<3.0.0,!=2.5.0,!=2.5.1)
Requires-Dist: pyquery (>=2.0.1,<3.0.0)
Requires-Dist: python-qbittorrent (>=0.4.3,<0.5.0)
Requires-Dist: tenacity (>=8.5.0,<9.0.0)
Requires-Dist: tinydb (>=4.8.0,<5.0.0)
Requires-Dist: yarl (>=1.11.1,<2.0.0)
Project-URL: Repository, https://github.com/Quan666/ELF_RSS
